LICENSE.txt
evo_package_pdf/__init__.py
evo_package_pdf/automation/api.yaml
evo_package_pdf/automation/entity.yaml
evo_package_pdf/control/CPdfApi.py
evo_package_pdf/control/__init__.py
evo_package_pdf/entity/EPdfInput.py
evo_package_pdf/entity/EPdfOutput.py
evo_package_pdf/entity/EPdfPage.py
evo_package_pdf/entity/__init__.py
evo_package_pdf/utility/IuPdf.py
evo_package_pdf/utility/UPdfApi.py
evo_package_pdf/utility/__init__.py
evo_package_pdf-2024.10.22328.dist-info/LICENSE.txt
evo_package_pdf-2024.10.22328.dist-info/METADATA
evo_package_pdf-2024.10.22328.dist-info/WHEEL
evo_package_pdf-2024.10.22328.dist-info/RECORD
